pydiderotlibs/__init__.py
pydiderotlibs/arithmetique.py
pydiderotlibs/chaines.py
pydiderotlibs/couleurs.py
pydiderotlibs/detection_collision.py
pydiderotlibs/entree.py
pydiderotlibs/fonctions_usuelles.py
pydiderotlibs/graphique.py
pydiderotlibs/graphique_dynamique.py
pydiderotlibs/graphique_statique.py
pydiderotlibs/images.py
pydiderotlibs/listes.py
pydiderotlibs/lycee.py
pydiderotlibs/math_lycee.py
pydiderotlibs/nmea.py
pydiderotlibs/repere.py
pydiderotlibs/stats_proba.py
pydiderotlibs/test_librairies.py
pydiderotlibs/touches_pygames.py
pydiderotlibs/trigo.py
pydiderotlibs/vecteurs.py
pydiderotlibs-0.0.23.dist-info/LICENSE
pydiderotlibs-0.0.23.dist-info/METADATA
pydiderotlibs-0.0.23.dist-info/WHEEL
pydiderotlibs-0.0.23.dist-info/top_level.txt
pydiderotlibs-0.0.23.dist-info/RECORD
