Metadata-Version: 2.1
Name: pydiderotlibs
Version: 0.0.23
Summary: Librairies utilisées dans l'enseignement de l'informatique
Home-page: https://github.com/Pydiderot/pydiderotlibs
Author: Professeurs de Mathématiques du lycée Denis Diderot (Marseille)
License: MIT
Keywords: python,teaching
Platform: UNKNOWN
Classifier: Programming Language :: Python :: 3
Classifier: Development Status :: 1 - Planning
Classifier: License :: OSI Approved :: MIT License
Classifier: Natural Language :: French
Classifier: Operating System :: OS Independent
Classifier: Topic :: Education
Requires-Python: >=3.0
Requires-Dist: pillow (>=9.2.0)
Requires-Dist: pygame (>=2.0)
Requires-Dist: pynmeagps (>=1.0.6)
